MANIFEST.in
README.rst
requirements.txt
setup.py
versions.py
SixIsles.egg-info/PKG-INFO
SixIsles.egg-info/SOURCES.txt
SixIsles.egg-info/dependency_links.txt
SixIsles.egg-info/requires.txt
SixIsles.egg-info/top_level.txt
sandbox/__init__.py
sandbox/test.py
sixisles/__init__.py
sixisles/adapter.py
sixisles/document.py
sixisles/exception.py
sixisles/structure.py
sixisles/types.py