Metadata-Version: 1.1
Name: SixIsles
Version: 0.0.3
Summary: PyMongo Based ActiveRecord Pattern O/R Mapper
Home-page: https://github.com/teitei-tk/SixIsles
Author: teitei-tk
Author-email: teitei.tk@gmail.com
License: MIT
Download-URL: https://github.com/teitei-tk/SixIsles/archive/master.zip
Keywords: orm,ormapper,o/r mapper,PyMongo,MongoDB
Platform: UNKNOWN
Classifier: Development Status :: 3 - Alpha
Classifier: License :: OSI Approved :: MIT License
Classifier: Programming Language :: Python
Classifier: Programming Language :: Python :: 2.6
Classifier: Programming Language :: Python :: 2.7
Classifier: Programming Language :: Python :: 3
Classifier: Topic :: Software Development
Classifier: Topic :: Database
Classifier: Topic :: Database :: Front-Ends
Classifier: Topic :: Software Development :: Libraries
